PyVSparse/_PyVSparse.cpython-39-x86_64-linux-gnu.so
PyVSparse/__init__.py
PyVSparse/ivcsc.py
PyVSparse/vcsc.py
pyvsparse-0.4.4.dist-info/METADATA
pyvsparse-0.4.4.dist-info/WHEEL
pyvsparse-0.4.4.dist-info/entry_points.txt
pyvsparse-0.4.4.dist-info/licenses/LICENSE
pyvsparse-0.4.4.dist-info/RECORD
