Metadata-Version: 2.1
Name: PyVSparse
Version: 0.4.4
Summary: A Python wrapper for IVSparse
Author-Email: Seth Wolfgang <wolfgangseth@gmail.com>
Project-URL: Ivsparse, https://github.com/Seth-Wolfgang/IVSparse
Project-URL: Pyvsparse, https://github.com/Seth-Wolfgang/PyVSparse
Project-URL: Pyvsparse-issues, https://github.com/Seth-Wolfgang/PyVSparse/issues
Requires-Python: >=3.9
Requires-Dist: numpy~=1.26.0
Requires-Dist: scipy~=1.11.2
Requires-Dist: matplotlib~=3.8.0
Requires-Dist: pytest; extra == "test"
Provides-Extra: test
License-File: LICENSE
